vka/__init__.py
vka/api.py
vka/bot.py
vka/base/__init__.py
vka/base/attrdict.py
vka/base/exception.py
vka/base/longpoll.py
vka/base/wrapper.py
vka/base/buiders/button.py
vka/base/buiders/keyboard.py
vka/chatbot/__init__.py
vka/chatbot/checking.py
vka/chatbot/context.py
vka/chatbot/filter.py
vka/chatbot/menu.py
vka/chatbot/push_button_menu.py
vka/chatbot/registration.py
vka/chatbot/storage.py
vka/chatbot/wrappers/messege.py
vka/chatbot/wrappers/user.py
vka-1.2.1.dist-info/METADATA
vka-1.2.1.dist-info/WHEEL
vka-1.2.1.dist-info/top_level.txt
vka-1.2.1.dist-info/RECORD
