Metadata-Version: 2.1
Name: vka
Version: 1.2.1
Summary: module for the vk api wrapper
Home-page: https://github.com/MrCreEper002/vka
Author: Major4ik
Author-email: 2772771882@mail.ru
Classifier: Programming Language :: Python :: 3.10
Classifier: Programming Language :: Python :: 3.11
Classifier: License :: OSI Approved :: MIT License
Classifier: Operating System :: OS Independent
Requires-Python: >=3.10
Requires-Dist: aiohttp (==3.8.1)
Requires-Dist: loguru (==0.6.0)
Requires-Dist: bs4 (==0.0.1)
